depgraph/__init__.py
depgraph/register.py
depgraph/backend/__init__.py
depgraph/backend/goal.py
depgraph/backend/rules.py
depgraph/backend/structs.py
pants_plugin_dep_graph-1.0.3.dist-info/METADATA
pants_plugin_dep_graph-1.0.3.dist-info/WHEEL
pants_plugin_dep_graph-1.0.3.dist-info/entry_points.txt
pants_plugin_dep_graph-1.0.3.dist-info/namespace_packages.txt
pants_plugin_dep_graph-1.0.3.dist-info/top_level.txt
pants_plugin_dep_graph-1.0.3.dist-info/RECORD
