Metadata-Version: 2.1
Name: pants-plugin-dep-graph
Version: 1.0.3
Summary: Pants plugin to export repository dependency graph.
Requires-Python: >=3.9
Requires-Dist: pantsbuild.pants (<2.17,>=2.16.0a0)
